celltypemark/__init__.py
celltypemark/mark.py
celltypemark/plotting.py
celltypemark/resource.py
celltypemark-0.3.0.dist-info/licenses/LICENSE
celltypemark-0.3.0.dist-info/METADATA
celltypemark-0.3.0.dist-info/WHEEL
celltypemark-0.3.0.dist-info/top_level.txt
celltypemark-0.3.0.dist-info/RECORD
