Metadata-Version: 2.4
Name: celltypemark
Version: 0.3.0
Summary: cell type annotation with scRNA sequencing data using any marker gene sets
Requires-Python: >=3.10
License-File: LICENSE
Requires-Dist: anndata>=0.11.4
Requires-Dist: requests>=2.32.3
Dynamic: license-file
